{
  "0e07710778a2": {
    "id": "0e07710778a2",
    "label": "13 CHE DE SAINGHIN, Verlinghem",
    "lat": 50.697152,
    "lng": 3.007093,
    "transactions": [
      {
        "date": "2021-10-26",
        "priceEur": 805000,
        "typeLocal": "Maison",
        "surfaceM2": 405,
        "isVefa": false
      }
    ]
  },
  "d47b2a099742": {
    "id": "d47b2a099742",
    "label": "10 CHE DE SAINGHIN, Verlinghem",
    "lat": 50.697336,
    "lng": 3.003778,
    "transactions": [
      {
        "date": "2024-04-25",
        "priceEur": 540000,
        "typeLocal": "Maison",
        "surfaceM2": 124,
        "isVefa": false
      }
    ]
  }
}