{
  "e930781b2872": {
    "id": "e930781b2872",
    "label": "41 RUE BLAISE PASCAL, Boujan-sur-Libron",
    "lat": 43.36827,
    "lng": 3.25205,
    "transactions": [
      {
        "date": "2020-12-04",
        "priceEur": 297800,
        "typeLocal": "Maison",
        "surfaceM2": 108,
        "isVefa": false
      },
      {
        "date": "2020-12-04",
        "priceEur": 297800,
        "typeLocal": "Maison",
        "surfaceM2": 108,
        "isVefa": false
      }
    ]
  },
  "2445da2fb76c": {
    "id": "2445da2fb76c",
    "label": "5 IMP MICHELET, Boujan-sur-Libron",
    "lat": 43.37077,
    "lng": 3.252272,
    "transactions": [
      {
        "date": "2021-02-01",
        "priceEur": 156000,
        "typeLocal": "Maison",
        "surfaceM2": 90,
        "isVefa": false
      }
    ]
  },
  "d202e3c0fd20": {
    "id": "d202e3c0fd20",
    "label": "27 RUE DES CATHARES, Boujan-sur-Libron",
    "lat": 43.368773,
    "lng": 3.255507,
    "transactions": [
      {
        "date": "2021-03-17",
        "priceEur": 429440,
        "typeLocal": "Maison",
        "surfaceM2": 165,
        "isVefa": false
      }
    ]
  },
  "cf000d7f708d": {
    "id": "cf000d7f708d",
    "label": "7 RUE DES ALBIGEOIS, Boujan-sur-Libron",
    "lat": 43.368405,
    "lng": 3.255356,
    "transactions": [
      {
        "date": "2024-12-02",
        "priceEur": 294438,
        "typeLocal": "Maison",
        "surfaceM2": 118,
        "isVefa": false
      },
      {
        "date": "2021-04-20",
        "priceEur": 269281,
        "typeLocal": "Maison",
        "surfaceM2": 118,
        "isVefa": false
      }
    ]
  },
  "04846c7f6c70": {
    "id": "04846c7f6c70",
    "label": "21 RUE DES CATHARES, Boujan-sur-Libron",
    "lat": 43.369451,
    "lng": 3.254739,
    "transactions": [
      {
        "date": "2021-05-03",
        "priceEur": 415000,
        "typeLocal": "Maison",
        "surfaceM2": 152,
        "isVefa": false
      }
    ]
  },
  "c25c8121f7b4": {
    "id": "c25c8121f7b4",
    "label": "50 RUE DE LA MARGERIDE, Boujan-sur-Libron",
    "lat": 43.367241,
    "lng": 3.257422,
    "transactions": [
      {
        "date": "2025-03-27",
        "priceEur": 126000,
        "typeLocal": "Appartement",
        "surfaceM2": 41,
        "isVefa": false
      },
      {
        "date": "2025-02-20",
        "priceEur": 170000,
        "typeLocal": "Appartement",
        "surfaceM2": 73,
        "isVefa": false
      },
      {
        "date": "2024-07-25",
        "priceEur": 119000,
        "typeLocal": "Appartement",
        "surfaceM2": 47,
        "isVefa": false
      },
      {
        "date": "2024-01-25",
        "priceEur": 145000,
        "typeLocal": "Appartement",
        "surfaceM2": 79,
        "isVefa": false
      },
      {
        "date": "2023-11-27",
        "priceEur": 130000,
        "typeLocal": "Appartement",
        "surfaceM2": 41,
        "isVefa": false
      },
      {
        "date": "2022-05-19",
        "priceEur": 131000,
        "typeLocal": "Appartement",
        "surfaceM2": 41,
        "isVefa": false
      },
      {
        "date": "2021-05-03",
        "priceEur": 182000,
        "typeLocal": "Appartement",
        "surfaceM2": 60,
        "isVefa": false
      }
    ]
  },
  "a1554a277105": {
    "id": "a1554a277105",
    "label": "61 BD PASTEUR, Boujan-sur-Libron",
    "lat": 43.369355,
    "lng": 3.253016,
    "transactions": [
      {
        "date": "2021-06-24",
        "priceEur": 271216,
        "typeLocal": "Maison",
        "surfaceM2": 90,
        "isVefa": false
      }
    ]
  },
  "42b304f201db": {
    "id": "42b304f201db",
    "label": "80 BD PASTEUR, Boujan-sur-Libron",
    "lat": 43.366774,
    "lng": 3.252181,
    "transactions": [
      {
        "date": "2021-08-05",
        "priceEur": 728000,
        "typeLocal": "Maison",
        "surfaceM2": 267,
        "isVefa": false
      },
      {
        "date": "2021-08-05",
        "priceEur": 728000,
        "typeLocal": "Maison",
        "surfaceM2": 267,
        "isVefa": false
      },
      {
        "date": "2021-08-05",
        "priceEur": 728000,
        "typeLocal": "Maison",
        "surfaceM2": 267,
        "isVefa": false
      },
      {
        "date": "2021-08-05",
        "priceEur": 728000,
        "typeLocal": "Maison",
        "surfaceM2": 267,
        "isVefa": false
      }
    ]
  },
  "f6e20a66db5f": {
    "id": "f6e20a66db5f",
    "label": "3 RUE DES ALBIGEOIS, Boujan-sur-Libron",
    "lat": 43.368061,
    "lng": 3.256353,
    "transactions": [
      {
        "date": "2021-08-27",
        "priceEur": 251900,
        "typeLocal": "Maison",
        "surfaceM2": 106,
        "isVefa": false
      }
    ]
  },
  "c3bea0367359": {
    "id": "c3bea0367359",
    "label": "12 RUE DES ALBIGEOIS, Boujan-sur-Libron",
    "lat": 43.367874,
    "lng": 3.256423,
    "transactions": [
      {
        "date": "2022-06-30",
        "priceEur": 468095,
        "typeLocal": "Maison",
        "surfaceM2": 169,
        "isVefa": false
      }
    ]
  },
  "0da58054655f": {
    "id": "0da58054655f",
    "label": "1 RUE DES CATHARES, Boujan-sur-Libron",
    "lat": 43.368781,
    "lng": 3.256452,
    "transactions": [
      {
        "date": "2022-08-01",
        "priceEur": 223160,
        "typeLocal": "Maison",
        "surfaceM2": 86,
        "isVefa": false
      }
    ]
  },
  "ee556055d772": {
    "id": "ee556055d772",
    "label": "53 BD PASTEUR, Boujan-sur-Libron",
    "lat": 43.369575,
    "lng": 3.252665,
    "transactions": [
      {
        "date": "2022-08-03",
        "priceEur": 290000,
        "typeLocal": "Maison",
        "surfaceM2": 163,
        "isVefa": false
      }
    ]
  },
  "cdde912dfc1c": {
    "id": "cdde912dfc1c",
    "label": "8 RUE DE L'ARDAILHOU, Boujan-sur-Libron",
    "lat": 43.371028,
    "lng": 3.256558,
    "transactions": [
      {
        "date": "2022-10-28",
        "priceEur": 477650,
        "typeLocal": "Maison",
        "surfaceM2": 122,
        "isVefa": false
      }
    ]
  },
  "c430491532e4": {
    "id": "c430491532e4",
    "label": "14 RUE DU LANGUEDOC, Boujan-sur-Libron",
    "lat": 43.370237,
    "lng": 3.254835,
    "transactions": [
      {
        "date": "2022-12-12",
        "priceEur": 332500,
        "typeLocal": "Maison",
        "surfaceM2": 130,
        "isVefa": false
      }
    ]
  },
  "676b35bb404c": {
    "id": "676b35bb404c",
    "label": "29 RUE DES CATHARES, Boujan-sur-Libron",
    "lat": 43.368769,
    "lng": 3.255911,
    "transactions": [
      {
        "date": "2024-09-25",
        "priceEur": 9310,
        "typeLocal": "Maison",
        "surfaceM2": 96,
        "isVefa": false
      },
      {
        "date": "2023-02-13",
        "priceEur": 348700,
        "typeLocal": "Maison",
        "surfaceM2": 96,
        "isVefa": false
      }
    ]
  },
  "a3d34f5613f4": {
    "id": "a3d34f5613f4",
    "label": "4 RUE DES ALBIGEOIS, Boujan-sur-Libron",
    "lat": 43.368686,
    "lng": 3.255164,
    "transactions": [
      {
        "date": "2023-07-20",
        "priceEur": 450000,
        "typeLocal": "Maison",
        "surfaceM2": 115,
        "isVefa": false
      }
    ]
  },
  "a72e220aa0ad": {
    "id": "a72e220aa0ad",
    "label": "6 IMP MICHELET, Boujan-sur-Libron",
    "lat": 43.370691,
    "lng": 3.252424,
    "transactions": [
      {
        "date": "2023-08-31",
        "priceEur": 46000,
        "typeLocal": "Maison",
        "surfaceM2": 90,
        "isVefa": false
      }
    ]
  },
  "b24382b74b79": {
    "id": "b24382b74b79",
    "label": "68 BD PASTEUR, Boujan-sur-Libron",
    "lat": 43.368499,
    "lng": 3.25313,
    "transactions": [
      {
        "date": "2023-09-28",
        "priceEur": 332800,
        "typeLocal": "Maison",
        "surfaceM2": 92,
        "isVefa": false
      }
    ]
  },
  "c1da603af43c": {
    "id": "c1da603af43c",
    "label": "10 RUE DES ALBIGEOIS, Boujan-sur-Libron",
    "lat": 43.367966,
    "lng": 3.256025,
    "transactions": [
      {
        "date": "2024-01-25",
        "priceEur": 409000,
        "typeLocal": "Maison",
        "surfaceM2": 120,
        "isVefa": false
      }
    ]
  },
  "099da7f4b60f": {
    "id": "099da7f4b60f",
    "label": "2 CHE DE LA CROISADE, Boujan-sur-Libron",
    "lat": 43.369864,
    "lng": 3.255979,
    "transactions": [
      {
        "date": "2024-03-13",
        "priceEur": 318000,
        "typeLocal": "Maison",
        "surfaceM2": 90,
        "isVefa": false
      }
    ]
  },
  "b106591fd144": {
    "id": "b106591fd144",
    "label": "12 RUE DE L'ARDAILHOU, Boujan-sur-Libron",
    "lat": 43.370764,
    "lng": 3.257226,
    "transactions": [
      {
        "date": "2024-05-24",
        "priceEur": 340000,
        "typeLocal": "Maison",
        "surfaceM2": 142,
        "isVefa": false
      }
    ]
  },
  "7fec4ecf72d9": {
    "id": "7fec4ecf72d9",
    "label": "9 RUE DES ALBIGEOIS, Boujan-sur-Libron",
    "lat": 43.3681,
    "lng": 3.255775,
    "transactions": [
      {
        "date": "2024-10-08",
        "priceEur": 460000,
        "typeLocal": "Maison",
        "surfaceM2": 197,
        "isVefa": false
      }
    ]
  },
  "86d5691f34c8": {
    "id": "86d5691f34c8",
    "label": "82 BD PASTEUR, Boujan-sur-Libron",
    "lat": 43.366422,
    "lng": 3.252976,
    "transactions": [
      {
        "date": "2024-12-26",
        "priceEur": 139860,
        "typeLocal": "Appartement",
        "surfaceM2": 44,
        "isVefa": false
      }
    ]
  },
  "16c65c3de55c": {
    "id": "16c65c3de55c",
    "label": "39 RUE BLAISE PASCAL, Boujan-sur-Libron",
    "lat": 43.368445,
    "lng": 3.252105,
    "transactions": [
      {
        "date": "2024-12-19",
        "priceEur": 270000,
        "typeLocal": "Maison",
        "surfaceM2": 113,
        "isVefa": false
      }
    ]
  },
  "4db07f98250c": {
    "id": "4db07f98250c",
    "label": "23 RUE DES CATHARES, Boujan-sur-Libron",
    "lat": 43.369208,
    "lng": 3.255087,
    "transactions": [
      {
        "date": "2025-03-28",
        "priceEur": 520000,
        "typeLocal": "Maison",
        "surfaceM2": 140,
        "isVefa": false
      }
    ]
  }
}