{
  "620dd94d13ea": {
    "id": "620dd94d13ea",
    "label": "13 RUE DU MOULIN, Mouchin",
    "lat": 50.51172,
    "lng": 3.284062,
    "transactions": [
      {
        "date": "2021-10-26",
        "priceEur": 205000,
        "typeLocal": "Maison",
        "surfaceM2": 62,
        "isVefa": false
      }
    ]
  },
  "6a8079bfa31c": {
    "id": "6a8079bfa31c",
    "label": "113 RUE DU MOULIN, Mouchin",
    "lat": 50.506694,
    "lng": 3.280238,
    "transactions": [
      {
        "date": "2022-11-25",
        "priceEur": 703500,
        "typeLocal": "Maison",
        "surfaceM2": 100,
        "isVefa": false
      }
    ]
  }
}