{
  "8faf3089ea7d": {
    "id": "8faf3089ea7d",
    "label": "1 SEN DU ROTIN, Eslettes",
    "lat": 49.53555,
    "lng": 1.051345,
    "transactions": [
      {
        "date": "2020-08-12",
        "priceEur": 137000,
        "typeLocal": "Maison",
        "surfaceM2": 128,
        "isVefa": false
      }
    ]
  },
  "0f8c387670c0": {
    "id": "0f8c387670c0",
    "label": "5147A FOND DES ALEURS, Eslettes",
    "lat": 49.53455,
    "lng": 1.046282,
    "transactions": [
      {
        "date": "2020-09-11",
        "priceEur": 159000,
        "typeLocal": "Maison",
        "surfaceM2": 80,
        "isVefa": false
      }
    ]
  },
  "520ecfe71d27": {
    "id": "520ecfe71d27",
    "label": "65 RTE DE MONTVILLE, Malaunay",
    "lat": 49.532533,
    "lng": 1.051373,
    "transactions": [
      {
        "date": "2022-08-03",
        "priceEur": 524800,
        "typeLocal": "Maison",
        "surfaceM2": 80,
        "isVefa": false
      },
      {
        "date": "2020-11-03",
        "priceEur": 289000,
        "typeLocal": "Maison",
        "surfaceM2": 80,
        "isVefa": false
      }
    ]
  },
  "6930952d39a6": {
    "id": "6930952d39a6",
    "label": "54 RTE D ESLETTES, Malaunay",
    "lat": 49.535054,
    "lng": 1.050207,
    "transactions": [
      {
        "date": "2024-12-17",
        "priceEur": 160500,
        "typeLocal": "Maison",
        "surfaceM2": 119,
        "isVefa": false
      },
      {
        "date": "2021-11-04",
        "priceEur": 314670,
        "typeLocal": "Maison",
        "surfaceM2": 149,
        "isVefa": false
      }
    ]
  },
  "3c09a88dcb0f": {
    "id": "3c09a88dcb0f",
    "label": "2397 RUE DU DOCTEUR MARTEL, Eslettes",
    "lat": 49.53564,
    "lng": 1.051466,
    "transactions": [
      {
        "date": "2021-11-18",
        "priceEur": 118000,
        "typeLocal": "Maison",
        "surfaceM2": 68,
        "isVefa": false
      }
    ]
  },
  "d1b1123f8daa": {
    "id": "d1b1123f8daa",
    "label": "22 RUE DE LA CLERETTE, Malaunay",
    "lat": 49.533281,
    "lng": 1.047267,
    "transactions": [
      {
        "date": "2021-01-14",
        "priceEur": 180000,
        "typeLocal": "Maison",
        "surfaceM2": 105,
        "isVefa": false
      }
    ]
  },
  "5303b562e86b": {
    "id": "5303b562e86b",
    "label": "5137 COTE DE MONVILLE, Eslettes",
    "lat": 49.539339,
    "lng": 1.054003,
    "transactions": [
      {
        "date": "2021-08-25",
        "priceEur": 82500,
        "typeLocal": "Maison",
        "surfaceM2": 96,
        "isVefa": false
      }
    ]
  },
  "5aed076bda76": {
    "id": "5aed076bda76",
    "label": "71 RTE D ESLETTES, Malaunay",
    "lat": 49.533875,
    "lng": 1.047284,
    "transactions": [
      {
        "date": "2022-04-15",
        "priceEur": 178000,
        "typeLocal": "Maison",
        "surfaceM2": 163,
        "isVefa": false
      }
    ]
  },
  "aedca182866c": {
    "id": "aedca182866c",
    "label": "1967 RUE DU DOCTEUR MARTEL, Montville",
    "lat": 49.539119,
    "lng": 1.05457,
    "transactions": [
      {
        "date": "2022-04-21",
        "priceEur": 80000,
        "typeLocal": "Maison",
        "surfaceM2": 60,
        "isVefa": false
      }
    ]
  },
  "3ba39a0adf93": {
    "id": "3ba39a0adf93",
    "label": "12 CHE DES ALEURS, Malaunay",
    "lat": 49.535147,
    "lng": 1.044072,
    "transactions": [
      {
        "date": "2022-05-24",
        "priceEur": 311600,
        "typeLocal": "Maison",
        "surfaceM2": 118,
        "isVefa": false
      }
    ]
  },
  "965609270085": {
    "id": "965609270085",
    "label": "1B SEN DU ROTIN, Eslettes",
    "lat": 49.535503,
    "lng": 1.051026,
    "transactions": [
      {
        "date": "2022-07-01",
        "priceEur": 212350,
        "typeLocal": "Maison",
        "surfaceM2": 90,
        "isVefa": false
      }
    ]
  },
  "159c96a5f8e3": {
    "id": "159c96a5f8e3",
    "label": "20 RUE DE LA CLERETTE, Malaunay",
    "lat": 49.533157,
    "lng": 1.047,
    "transactions": [
      {
        "date": "2023-04-20",
        "priceEur": 225000,
        "typeLocal": "Maison",
        "surfaceM2": 105,
        "isVefa": false
      }
    ]
  },
  "bb7d69f63d79": {
    "id": "bb7d69f63d79",
    "label": "12 RUE DE LA CLERETTE, Malaunay",
    "lat": 49.53271,
    "lng": 1.04612,
    "transactions": [
      {
        "date": "2023-05-25",
        "priceEur": 206200,
        "typeLocal": "Maison",
        "surfaceM2": 105,
        "isVefa": false
      }
    ]
  },
  "72b71f7f012a": {
    "id": "72b71f7f012a",
    "label": "14 RUE DE LA CLERETTE, Malaunay",
    "lat": 49.532776,
    "lng": 1.04645,
    "transactions": [
      {
        "date": "2023-08-21",
        "priceEur": 210000,
        "typeLocal": "Maison",
        "surfaceM2": 105,
        "isVefa": false
      }
    ]
  },
  "54fe334dc7db": {
    "id": "54fe334dc7db",
    "label": "2350 RUE DU DOCTEUR MARTEL, Eslettes",
    "lat": 49.536547,
    "lng": 1.051355,
    "transactions": [
      {
        "date": "2024-06-11",
        "priceEur": 291000,
        "typeLocal": "Maison",
        "surfaceM2": 160,
        "isVefa": false
      }
    ]
  },
  "b18fc3f0db5e": {
    "id": "b18fc3f0db5e",
    "label": "4D COTE DE DIEPPE, Malaunay",
    "lat": 49.534596,
    "lng": 1.043976,
    "transactions": [
      {
        "date": "2024-08-05",
        "priceEur": 189000,
        "typeLocal": "Maison",
        "surfaceM2": 70,
        "isVefa": false
      }
    ]
  },
  "afdcf38ac1da": {
    "id": "afdcf38ac1da",
    "label": "19 RUE DE LA CLERETTE, Malaunay",
    "lat": 49.5331,
    "lng": 1.046932,
    "transactions": [
      {
        "date": "2024-12-27",
        "priceEur": 183000,
        "typeLocal": "Maison",
        "surfaceM2": 105,
        "isVefa": false
      }
    ]
  }
}